tkpod/core/__init__.py
tkpod/core/interface.py
tkpod/core/types.py
tkpod/core/utils.py
tkpod_core-0.1.0.dist-info/METADATA
tkpod_core-0.1.0.dist-info/RECORD
tkpod_core-0.1.0.dist-info/WHEEL
tkpod_core-0.1.0.dist-info/top_level.txt
