Metadata-Version: 2.1
Name: tkpod-core
Version: 0.1.0
Summary: Core libraries for the `tkpod` project.
Home-page: https://gitlab.com/tkpod/tkpod-core
Author: Alexey Strokach
Author-email: alex.strokach@utoronto.ca
License: UNKNOWN
Keywords: tkpod
Platform: UNKNOWN
Classifier: Development Status :: 2 - Pre-Alpha
Classifier: Intended Audience :: Developers
Classifier: Natural Language :: English
Classifier: Programming Language :: Python :: 3.6
